lunar_python/EightChar.py
lunar_python/Foto.py
lunar_python/FotoFestival.py
lunar_python/Fu.py
lunar_python/Holiday.py
lunar_python/JieQi.py
lunar_python/Lunar.py
lunar_python/LunarMonth.py
lunar_python/LunarTime.py
lunar_python/LunarYear.py
lunar_python/NineStar.py
lunar_python/ShuJiu.py
lunar_python/Solar.py
lunar_python/SolarHalfYear.py
lunar_python/SolarMonth.py
lunar_python/SolarSeason.py
lunar_python/SolarWeek.py
lunar_python/SolarYear.py
lunar_python/Tao.py
lunar_python/TaoFestival.py
lunar_python/__init__.py
lunar_python/eightchar/DaYun.py
lunar_python/eightchar/LiuNian.py
lunar_python/eightchar/LiuYue.py
lunar_python/eightchar/XiaoYun.py
lunar_python/eightchar/Yun.py
lunar_python/eightchar/__init__.py
lunar_python/util/FotoUtil.py
lunar_python/util/HolidayUtil.py
lunar_python/util/LunarUtil.py
lunar_python/util/ShouXingUtil.py
lunar_python/util/SolarUtil.py
lunar_python/util/TaoUtil.py
lunar_python/util/__init__.py
lunar_python_zmt-1.4.9.dist-info/licenses/LICENSE
lunar_python_zmt-1.4.9.dist-info/METADATA
lunar_python_zmt-1.4.9.dist-info/WHEEL
lunar_python_zmt-1.4.9.dist-info/top_level.txt
lunar_python_zmt-1.4.9.dist-info/RECORD
