Metadata-Version: 2.4
Name: lunar_python_zmt
Version: 1.4.9
Summary: lunar is a calendar library for Solar and Chinese Lunar.
Author-email: 6tail <6tail@6tail.cn>, zhimingtong <zhangzangqian@chenzexj.com>
License: MIT
Project-URL: Homepage, https://github.com/6tail/lunar-python
Keywords: solar,lunar,calendar
License-File: LICENSE
Dynamic: license-file
